opentelemetry/instrumentation/anthropic/__init__.py
opentelemetry/instrumentation/anthropic/config.py
opentelemetry/instrumentation/anthropic/streaming.py
opentelemetry/instrumentation/anthropic/utils.py
opentelemetry/instrumentation/anthropic/version.py
opentelemetry/instrumentation/chromadb/__init__.py
opentelemetry/instrumentation/chromadb/config.py
opentelemetry/instrumentation/chromadb/utils.py
opentelemetry/instrumentation/chromadb/version.py
opentelemetry/instrumentation/chromadb/wrapper.py
opentelemetry/instrumentation/langchain/__init__.py
opentelemetry/instrumentation/langchain/config.py
opentelemetry/instrumentation/langchain/custom_chat_wrapper.py
opentelemetry/instrumentation/langchain/custom_llm_wrapper.py
opentelemetry/instrumentation/langchain/task_wrapper.py
opentelemetry/instrumentation/langchain/utils.py
opentelemetry/instrumentation/langchain/version.py
opentelemetry/instrumentation/langchain/workflow_wrapper.py
opentelemetry/instrumentation/litellm/__init__.py
opentelemetry/instrumentation/litellm/utils.py
opentelemetry/instrumentation/litellm/version.py
opentelemetry/instrumentation/litellm/shared/__init__.py
opentelemetry/instrumentation/litellm/shared/chat_wrappers.py
opentelemetry/instrumentation/litellm/shared/completion_wrappers.py
opentelemetry/instrumentation/litellm/shared/config.py
opentelemetry/instrumentation/litellm/shared/embeddings_wrappers.py
opentelemetry/instrumentation/litellm/shared/image_gen_wrappers.py
opentelemetry/instrumentation/litellm/v0/__init__.py
opentelemetry/instrumentation/litellm/v1/__init__.py
opentelemetry/instrumentation/litellm/v1/assistant_wrappers.py
opentelemetry/instrumentation/litellm/v1/event_handler_wrapper.py
opentelemetry/instrumentation/llamaindex/__init__.py
opentelemetry/instrumentation/llamaindex/base_agent_instrumentor.py
opentelemetry/instrumentation/llamaindex/base_embedding_instrumentor.py
opentelemetry/instrumentation/llamaindex/base_retriever_instrumentor.py
infrastackai_opentelemetry-0.0.2.dist-info/LICENSE
infrastackai_opentelemetry-0.0.2.dist-info/METADATA
infrastackai_opentelemetry-0.0.2.dist-info/WHEEL
infrastackai_opentelemetry-0.0.2.dist-info/top_level.txt
infrastackai_opentelemetry-0.0.2.dist-info/RECORD
